uoshardware/__init__.py
uoshardware/abstractions.py
uoshardware/api.py
uoshardware/devices/__init__.py
uoshardware/devices/_arduino.py
uoshardware/interface/__init__.py
uoshardware/interface/serial.py
uoshardware/interface/stub.py
uos_hardware-0.6.0.dist-info/LICENSE.md
uos_hardware-0.6.0.dist-info/METADATA
uos_hardware-0.6.0.dist-info/WHEEL
uos_hardware-0.6.0.dist-info/RECORD
