Metadata-Version: 2.1
Name: uos-hardware
Version: 0.6.0
Summary: A hardware abstraction layer for microcontrollers running UOS compliant firmware.
Home-page: https://github.com/CreatingNull/UOS-Hardware
License: MIT
Author: nulltek
Author-email: steve.public@nulltek.xyz
Requires-Python: >=3.10,<4.0
Classifier: License :: OSI Approved :: MIT License
Classifier: Programming Language :: Python :: 3
Classifier: Programming Language :: Python :: 3.10
Classifier: Programming Language :: Python :: 3.11
Requires-Dist: pyserial (>=3.5,<4.0)
Project-URL: Documentation, https://uos-hardware.nulltek.xyz
